Sagittarius/__init__.py
Sagittarius/api_utils.py
Sagittarius/simulate_measurements.py
Sagittarius/simulate_measurements_webserver.py
Sagittarius/webserver_files/EvoDevo:Sagittarius_pretrained.pth
Sagittarius/webserver_files/EvoDevo:attribute.txt
Sagittarius/webserver_files/EvoDevo:expression.txt
Sagittarius/webserver_files/EvoDevo:gene_name_mapping.txt
Sagittarius/webserver_files/EvoDevo:idx_to_gene.txt
Sagittarius/webserver_files/EvoDevo_config.json
Sagittarius/webserver_files/EvoDevo_dataset.py
Sagittarius/webserver_files/EvoDevo_utils.py
Sagittarius/webserver_files/Sagittarius.py
Sagittarius/webserver_files/non_stationary_mask.txt
Sagittarius_api-0.17.dist-info/METADATA
Sagittarius_api-0.17.dist-info/WHEEL
Sagittarius_api-0.17.dist-info/top_level.txt
Sagittarius_api-0.17.dist-info/RECORD
